netsnmp_cffi.libs/libcrypto-bdaed0ea.so.1.1.1k
netsnmp_cffi.libs/libnetsnmp-25bcaca1.so.40.1.0
netsnmp_cffi.libs/libssl-60250281.so.1.1.1k
netsnmpy/__init__.py
netsnmpy/_netsnmp.abi3.so
netsnmpy/annotations.py
netsnmpy/constants.py
netsnmpy/errors.py
netsnmpy/netsnmp.py
netsnmpy/netsnmp_ffi.py
netsnmpy/oids.py
netsnmpy/session.py
netsnmpy/trapsession.py
netsnmpy/version.py
netsnmpy/programs/__init__.py
netsnmpy/programs/asnmpget.py
netsnmpy/programs/asnmpgetbulk.py
netsnmpy/programs/snmptranslate.py
netsnmpy/programs/subtreedata.py
netsnmpy/programs/trapd.py
netsnmp_cffi-0.1.3.dist-info/METADATA
netsnmp_cffi-0.1.3.dist-info/WHEEL
netsnmp_cffi-0.1.3.dist-info/entry_points.txt
netsnmp_cffi-0.1.3.dist-info/top_level.txt
netsnmp_cffi-0.1.3.dist-info/RECORD
netsnmp_cffi-0.1.3.dist-info/licenses/LICENSE
