Metadata-Version: 2.4
Name: netsnmp-cffi
Version: 0.1.3
Summary: CFFI interface to Net-SNMP
Author-email: Sikt - Norwegian Agency for Shared Services in Education and Research <kontakt@sikt.no>
Maintainer-email: Morten Brekkevold <morten.brekkevold@sikt.no>
License-Expression: Apache-2.0
Project-URL: Homepage, https://github.com/Uninett/netsnmp-cffi
Platform: any
Classifier: Intended Audience :: Information Technology
Classifier: Intended Audience :: Developers
Classifier: Development Status :: 3 - Alpha
Classifier: Programming Language :: Python :: 3 :: Only
Classifier: Programming Language :: Python :: 3.9
Classifier: Programming Language :: Python :: 3.10
Classifier: Programming Language :: Python :: 3.11
Classifier: Programming Language :: Python :: 3.12
Classifier: Topic :: System :: Networking :: Monitoring
Requires-Python: >=3.9
License-File: LICENSE
Requires-Dist: cffi
Dynamic: license-file
